{
  "template": "infrastructure_blueprint",
  "id": "asteroid_station_shell",
  "name": "Asteroid Station Shell",
  "description": "Hollowed asteroid shell providing radiation shielding and pressurizable volume for station construction.",
  "category": "unpopulated_infrastructure",
  "properties": ["high_radiation_shielding", "pressurizable_volume"],
  "creation_requirement": "hollowing_equipment_task_completion",
  "slag_ratio": 0.70,
  "shielded_volume_ratio": 0.30,
  "metadata": {
    "version": "1.0",
    "type": "infrastructure",
    "category": "unpopulated",
    "template_compliance": "infrastructure_blueprint"
  }
}